psite/__init__.py
psite/coverage.py
psite/main.py
psite/pbam.py
psite/predict.py
psite/setp.py
psite/train.py
psite/utils.py
psite-0.1.6.dist-info/LICENSE
psite-0.1.6.dist-info/METADATA
psite-0.1.6.dist-info/WHEEL
psite-0.1.6.dist-info/entry_points.txt
psite-0.1.6.dist-info/top_level.txt
psite-0.1.6.dist-info/RECORD
