Metadata-Version: 2.1
Name: psite
Version: 0.1.6
Summary: Model-based inference of P-site offsets
Home-page: https://github.com/gxelab/psite
Author: Hong Zhang (mt1022)
Author-email: gxelab@163.com
Project-URL: Bug Tracker, https://github.com/gxelab/psite/issues
Classifier: Programming Language :: Python :: 3
Classifier: License :: OSI Approved :: MIT License
Classifier: Operating System :: OS Independent
Classifier: Intended Audience :: Science/Research
Classifier: Topic :: Scientific/Engineering :: Bio-Informatics
Requires-Python: >=3.9
License-File: LICENSE
Requires-Dist: numpy >=1.21.2
Requires-Dist: pandas >=1.3.4
Requires-Dist: scikit-learn >=1.1.1
Requires-Dist: biopython >=1.79
Requires-Dist: pysam >=0.17.0
Requires-Dist: click >=8.1.2
Requires-Dist: pyBigWig >=0.3.18
Requires-Dist: seaborn >=0.11.0
